osp/__init__.py
osp/cli/__init__.py
osp/cli/main.py
osp/core/__init__.py
osp/core/device.py
osp/download/__init__.py
osp/download/bulk.py
osp/download/search.py
osp/download/spotify.py
osp/download/youtube.py
osp_tools-0.2.0.dist-info/licenses/LICENSE
tests/__init__.py
tests/test_cli.py
tests/test_spotify.py
osp_tools-0.2.0.dist-info/METADATA
osp_tools-0.2.0.dist-info/WHEEL
osp_tools-0.2.0.dist-info/entry_points.txt
osp_tools-0.2.0.dist-info/top_level.txt
osp_tools-0.2.0.dist-info/RECORD
