Metadata-Version: 2.4
Name: osp-tools
Version: 0.2.0
Summary: OpenSwim Pro Tools - Manage and download songs for your OpenSwim Pro / 2
Author-email: Ege Türker <egeturker34@icloud.com>
License: MIT License
Project-URL: Homepage, https://github.com/1etu/osp-tools
Project-URL: Repository, https://github.com/1etu/osp-tools
Project-URL: Issues, https://github.com/1etu/osp-tools/issues
Keywords: openswim,mp3,swimming,music,download
Classifier: Development Status :: 3 - Alpha
Classifier: Environment :: Console
Classifier: Intended Audience :: End Users/Desktop
Classifier: License :: OSI Approved :: MIT License
Classifier: Operating System :: OS Independent
Classifier: Programming Language :: Python :: 3
Classifier: Programming Language :: Python :: 3.10
Classifier: Programming Language :: Python :: 3.11
Classifier: Programming Language :: Python :: 3.12
Classifier: Topic :: Multimedia :: Sound/Audio
Requires-Python: >=3.9
License-File: LICENSE
Requires-Dist: click>=8.0
Requires-Dist: yt-dlp>=2024.0
Requires-Dist: rich>=13.0
Provides-Extra: dev
Requires-Dist: pytest>=7.0; extra == "dev"
Requires-Dist: ruff>=0.1; extra == "dev"
Dynamic: license-file
